seamm/__init__.py
seamm/__main__.py
seamm/_version.py
seamm/builtins.py
seamm/dashboard_handler.py
seamm/data.py
seamm/flowchart.py
seamm/graph.py
seamm/join_node.py
seamm/node.py
seamm/parameters.py
seamm/plugin_manager.py
seamm/seammrc.py
seamm/split_node.py
seamm/standard_parameters.py
seamm/start_node.py
seamm/tk_edge.py
seamm/tk_flowchart.py
seamm/tk_job_handler.py
seamm/tk_join_node.py
seamm/tk_node.py
seamm/tk_open.py
seamm/tk_publish.py
seamm/tk_split_node.py
seamm/tk_start_node.py
seamm/variables.py
seamm/data/SEAMM logo.png
seamm/data/SEAMM.png
seamm/data/SEAMM.svg
seamm/data/SEAMM_notext.png
seamm/data/SEAMM_notext.svg
seamm/data/dashboards.ini
seamm/templates/band_structure.graph_template
seamm/templates/band_structure.html_template
seamm/templates/line.graph_template
seamm/templates/line.html_template
seamm/templates/surface.graph_template
seamm/templates/surface.html_template
seamm-2025.10.22.dist-info/licenses/AUTHORS.rst
seamm-2025.10.22.dist-info/licenses/LICENSE
seamm-2025.10.22.dist-info/METADATA
seamm-2025.10.22.dist-info/WHEEL
seamm-2025.10.22.dist-info/entry_points.txt
seamm-2025.10.22.dist-info/top_level.txt
seamm-2025.10.22.dist-info/RECORD
