Metadata-Version: 2.4
Name: seamm
Version: 2025.10.22
Summary: The core of the SEAMM environment and graphical interface.
Home-page: https://github.com/molssi-seamm/seamm
Author: Paul Saxe
Author-email: psaxe@molssi.org
License: GNU Lesser General Public License v3
Keywords: seamm
Platform: Linux
Platform: Mac OS-X
Platform: Unix
Platform: Windows
Classifier: Development Status :: 5 - Production/Stable
Classifier: Intended Audience :: Developers
Classifier: Topic :: Scientific/Engineering :: Chemistry
Classifier: Topic :: Scientific/Engineering :: Physics
Classifier: License :: OSI Approved :: GNU Lesser General Public License v3 or later (LGPLv3+)
Classifier: Natural Language :: English
Classifier: Programming Language :: Python :: 3 :: Only
Classifier: Programming Language :: Python :: 3.8
Classifier: Programming Language :: Python :: 3.9
License-File: LICENSE
License-File: AUTHORS.rst
Requires-Dist: bibtexparser
Requires-Dist: fasteners
Requires-Dist: humanize
Requires-Dist: jinja2
Requires-Dist: molsystem
Requires-Dist: numpy
Requires-Dist: packaging
Requires-Dist: pandas
Requires-Dist: pillow
Requires-Dist: pmw
Requires-Dist: py-cpuinfo
Requires-Dist: python-dateutil
Requires-Dist: pyuca
Requires-Dist: reference_handler
Requires-Dist: seamm-dashboard-client
Requires-Dist: seamm-datastore
Requires-Dist: seamm-util
Requires-Dist: seamm-widgets
Requires-Dist: stevedore
Dynamic: author
Dynamic: author-email
Dynamic: classifier
Dynamic: description
Dynamic: home-page
Dynamic: keywords
Dynamic: license
Dynamic: license-file
Dynamic: platform
Dynamic: requires-dist
Dynamic: summary
